mini_patch-1.0.0.dist-info/RECORD
mini_patch-1.0.0.dist-info/WHEEL
mini_patch-1.0.0.dist-info/metadata.json
mini_patch-1.0.0.dist-info/DESCRIPTION.rst
mini_patch-1.0.0.dist-info/top_level.txt
mini_patch-1.0.0.dist-info/METADATA
mini_patch/__init__.py
