Metadata-Version: 2.0
Name: mini-patch
Version: 1.0.0
Summary: Tiny diffs using difflib's SequenceMatcher
Home-page: https://github.com/edmund-huber/mini_patch
Author: Edmund Huber
Author-email: me@ehuber.info
License: UNKNOWN
Platform: UNKNOWN
Classifier: Programming Language :: Python :: 2
Classifier: License :: OSI Approved :: MIT License
Classifier: Operating System :: OS Independent
